getpaid_payu/__init__.py
getpaid_payu/apps.py
getpaid_payu/client.py
getpaid_payu/processor.py
getpaid_payu/templates/getpaid_payu/payment_post_form.html
getpaid_payu/types.py
getpaid_payu/urls.py
getpaid_payu/views.py
django_getpaid_payu-0.2.1.dist-info/LICENSE
django_getpaid_payu-0.2.1.dist-info/WHEEL
django_getpaid_payu-0.2.1.dist-info/METADATA
django_getpaid_payu-0.2.1.dist-info/RECORD
