Metadata-Version: 2.1
Name: django-getpaid-payu
Version: 0.2.1
Summary: Django-GetPaid plugin for PayU service.
Home-page: https://github.com/django-getpaid/django-getpaid-payu
License: MIT
Author: Dominik Kozaczko
Author-email: dominik@kozaczko.info
Requires-Python: >=3.7,<4.0
Classifier: License :: OSI Approved :: MIT License
Classifier: Programming Language :: Python :: 3
Classifier: Programming Language :: Python :: 3.7
Classifier: Programming Language :: Python :: 3.8
Classifier: Programming Language :: Python :: 3.9
Classifier: Programming Language :: Python :: 3.10
Provides-Extra: test
Requires-Dist: codecov (>=2.1.11,<3.0.0); extra == "test"
Requires-Dist: coverage (>=5.5,<6.0); extra == "test"
Requires-Dist: django-getpaid (>=2.3.0,<3.0.0)
Requires-Dist: pytest (>=6.2.4,<7.0.0); extra == "test"
Requires-Dist: pytest-cov (>=2.12.1,<3.0.0); extra == "test"
Requires-Dist: pytest-django (>=4.4.0,<5.0.0); extra == "test"
Requires-Dist: pytest-factoryboy (>=2.1.0,<3.0.0); extra == "test"
Requires-Dist: requests (>=2.25.1,<3.0.0); extra == "test"
Requires-Dist: requests-mock (>=1.9.3,<2.0.0); extra == "test"
Requires-Dist: swapper (>=1.1.2,<2.0.0)
Requires-Dist: typing-extensions (>=3.10.0,<4.0.0)
Project-URL: Repository, https://github.com/django-getpaid/django-getpaid-payu
